README.rst
setup.py
spambayes_lite/CorePlugin.py
spambayes_lite/CoreUI.py
spambayes_lite/Corpus.py
spambayes_lite/CostCounter.py
spambayes_lite/Dibbler.py
spambayes_lite/FileCorpus.py
spambayes_lite/Histogram.py
spambayes_lite/ImageStripper.py
spambayes_lite/ImapUI.py
spambayes_lite/MoinSecurityPolicy.py
spambayes_lite/Options.py
spambayes_lite/OptionsClass.py
spambayes_lite/ProxyUI.py
spambayes_lite/PyMeldLite.py
spambayes_lite/ServerUI.py
spambayes_lite/Stats.py
spambayes_lite/TestDriver.py
spambayes_lite/TestToolsUI.py
spambayes_lite/Tester.py
spambayes_lite/UserInterface.py
spambayes_lite/Version.py
spambayes_lite/XMLRPCPlugin.py
spambayes_lite/__init__.py
spambayes_lite/cdb.py
spambayes_lite/cdb_classifier.py
spambayes_lite/chi2.py
spambayes_lite/classifier.py
spambayes_lite/compatcsv.py
spambayes_lite/compatheapq.py
spambayes_lite/compatsets.py
spambayes_lite/dnscache.py
spambayes_lite/hammie.py
spambayes_lite/hammiebulk.py
spambayes_lite/i18n.py
spambayes_lite/mboxutils.py
spambayes_lite/message.py
spambayes_lite/mongo_storage.py
spambayes_lite/msgs.py
spambayes_lite/oe_mailbox.py
spambayes_lite/optimize.py
spambayes_lite/port.py
spambayes_lite/postfixproxy.py
spambayes_lite/safepickle.py
spambayes_lite/smtpproxy.py
spambayes_lite/storage.py
spambayes_lite/tokenizer.py
spambayes_lite.egg-info/PKG-INFO
spambayes_lite.egg-info/SOURCES.txt
spambayes_lite.egg-info/dependency_links.txt
spambayes_lite.egg-info/requires.txt
spambayes_lite.egg-info/top_level.txt
spambayes_lite/core_resources/README_txt.py
spambayes_lite/core_resources/__init__.py
spambayes_lite/core_resources/classify_gif.py
spambayes_lite/core_resources/config_gif.py
spambayes_lite/core_resources/helmet_gif.py
spambayes_lite/core_resources/help_gif.py
spambayes_lite/core_resources/message_gif.py
spambayes_lite/core_resources/query_gif.py
spambayes_lite/core_resources/scanning__init__.py
spambayes_lite/core_resources/status_gif.py
spambayes_lite/core_resources/train_gif.py
spambayes_lite/core_resources/ui_html.py
spambayes_lite/core_resources/ui_psp.py
spambayes_lite/languages/__init__.py
spambayes_lite/languages/de/__init__.py
spambayes_lite/languages/de/DIALOGS/__init__.py
