Metadata-Version: 1.1
Name: spambayes-lite
Version: 1.0.0b7
Summary: Bare-bones spam classification library based on a modified version of SpamBayes.
Home-page: https://github.com/dbrandt/spambayes-lite
Author: Daniel Brandt
Author-email: me@dbrandt.se
License: PSFL
Platform: UNKNOWN
Classifier: Development Status :: 4 - Beta
Classifier: License :: OSI Approved :: Python Software Foundation License
Classifier: Operating System :: POSIX
Classifier: Operating System :: MacOS :: MacOS X
Classifier: Natural Language :: English
Classifier: Programming Language :: Python
Classifier: Intended Audience :: Developers
Classifier: Topic :: Software Development :: Libraries
Classifier: Topic :: Text Processing :: Filters
